leakcheck.py
leakcheck-2.0.0.data/scripts/leakcheck
leakcheck-2.0.0.dist-info/LICENSE
leakcheck-2.0.0.dist-info/METADATA
leakcheck-2.0.0.dist-info/WHEEL
leakcheck-2.0.0.dist-info/top_level.txt
leakcheck-2.0.0.dist-info/RECORD
