Metadata-Version: 2.1
Name: leakcheck
Version: 2.0.0
Summary: Python wrapper for LeakCheck API & also a CLI tool
Home-page: https://github.com/LeakCheck/leakcheck-api
Author: LeakCheck
Author-email: the@leakcheck.net
Classifier: Programming Language :: Python :: 3
Classifier: License :: OSI Approved :: MIT License
Classifier: Operating System :: OS Independent
Requires-Python: >=3.5
License-File: LICENSE
Requires-Dist: requests
Requires-Dist: pysocks
Requires-Dist: tabulate
